LICENSE.txt
MANIFEST.in
README.md
requirements.txt
setup.py
tests/test_cache.py
tests/test_cli.py
tests/test_unpywall.py
tests/test_utils.py
unpywall/__init__.py
unpywall/__main__.py
unpywall/cache.py
unpywall/utils.py
unpywall.egg-info/PKG-INFO
unpywall.egg-info/SOURCES.txt
unpywall.egg-info/dependency_links.txt
unpywall.egg-info/entry_points.txt
unpywall.egg-info/not-zip-safe
unpywall.egg-info/requires.txt
unpywall.egg-info/top_level.txt