Metadata-Version: 2.1
Name: unpywall
Version: 0.2.3
Summary: Interfacing the Unpaywall Database with Python
Home-page: https://github.com/unpywall/unpywall
Author: Nick Haupka, bganglia
Author-email: nick.haupka@gmail.com, bganglia892@gmail.com
License: MIT
Project-URL: Documentation, https://unpywall.readthedocs.io/en/latest/
Project-URL: Source, https://github.com/unpywall/unpywall
Project-URL: Tracker, https://github.com/unpywall/unpywall/issues
Keywords: Unpaywall,Open Access,full text
Classifier: Development Status :: 3 - Alpha
Classifier: License :: OSI Approved :: MIT License
Classifier: Operating System :: OS Independent
Classifier: Programming Language :: Python :: 3.7
Classifier: Programming Language :: Python :: 3.8
Classifier: Programming Language :: Python :: 3.9
License-File: LICENSE.txt
Requires-Dist: pandas
Requires-Dist: requests
Provides-Extra: dev
Requires-Dist: pytest; extra == "dev"
Requires-Dist: coverage; extra == "dev"
Requires-Dist: pytest-cov; extra == "dev"
Requires-Dist: sphinx; extra == "dev"
Requires-Dist: alabaster; extra == "dev"
